mms_monthly_cli/__init__.py
mms_monthly_cli/cli.py
mms_monthly_cli/mms_monthly.py
mms_monthly_cli-1.1.0.dist-info/LICENSE
mms_monthly_cli-1.1.0.dist-info/METADATA
mms_monthly_cli-1.1.0.dist-info/WHEEL
mms_monthly_cli-1.1.0.dist-info/entry_points.txt
mms_monthly_cli-1.1.0.dist-info/RECORD
