Metadata-Version: 2.1
Name: mms-monthly-cli
Version: 1.1.0
Summary: A package and CLI utility to check for available data and download tables from AEMO's Monthly Data Archive
Home-page: https://github.com/prakaa/mms-monthly-cli
License: GPL-3.0-or-later
Author: prakaa
Author-email: abiprakash007@gmail.com
Requires-Python: >=3.8,<4.0
Classifier: License :: OSI Approved :: GNU General Public License v3 or later (GPLv3+)
Classifier: Programming Language :: Python :: 3
Classifier: Programming Language :: Python :: 3.8
Classifier: Programming Language :: Python :: 3.9
Classifier: Programming Language :: Python :: 3.10
Classifier: Programming Language :: Python :: 3.11
Classifier: Programming Language :: Python :: 3.12
Requires-Dist: beautifulsoup4 (>=4,<5)
Requires-Dist: requests (>=2,<3)
Requires-Dist: tqdm (>=4,<5)
Requires-Dist: typer[all] (>=0.9.0,<0.10.0)
Requires-Dist: user-agent (>=0.1,<0.2)
